satif_ai/__init__.py
satif_ai/adapters/__init__.py
satif_ai/adapters/tidy.py
satif_ai/standardize.py
satif_ai/standardizers/__init__.py
satif_ai/standardizers/ai.py
satif_ai/standardizers/ai_csv.py
satif_ai/standardizers/ai_xlsx.py
satif_ai/transform.py
satif_ai/transformation_builders/__init__.py
satif_ai/transformation_builders/syncpulse.py
satif_ai/utils/__init__.py
satif_ai/utils/merge_sdif.py
satif_ai/utils/openai_mcp.py
satif_ai/utils/zip.py
satif_ai-0.2.12.dist-info/LICENSE
satif_ai-0.2.12.dist-info/METADATA
satif_ai-0.2.12.dist-info/WHEEL
satif_ai-0.2.12.dist-info/entry_points.txt
satif_ai-0.2.12.dist-info/RECORD
